Metadata-Version: 1.0
Name: pronomial
Version: 0.0.3
Summary: pronomial postag/word_gender based coreference solver
Home-page: https://github.com/OpenJarbas/pronomial
Author: jarbasAi
Author-email: jarbasai@mailfence.com
License: apache-2.0
Platform: UNKNOWN
